pmwui/__init__.py
pmwui/simple.py
polymarker_webui-0.0.1.dist-info/LICENSE
polymarker_webui-0.0.1.dist-info/METADATA
polymarker_webui-0.0.1.dist-info/WHEEL
polymarker_webui-0.0.1.dist-info/entry_points.txt
polymarker_webui-0.0.1.dist-info/top_level.txt
polymarker_webui-0.0.1.dist-info/RECORD
