Metadata-Version: 2.2
Name: polymarker-webui
Version: 0.0.1
Summary: A web interface for polymarker
Author-email: Rob Ellis <rob.ellis@jic.ac.uk>
Maintainer-email: Rob Ellis <rob.ellis@jic.ac.uk>
License: MIT License
Classifier: Development Status :: 3 - Alpha
Classifier: License :: OSI Approved :: MIT License
Classifier: Programming Language :: Python :: 3.9
Requires-Python: >=3.9
License-File: LICENSE
